yardstick_benchmark/__init__.py
yardstick_benchmark/clean.yml
yardstick_benchmark/fetch.yml
yardstick_benchmark/games/__init__.py
yardstick_benchmark/games/minecraft/__init__.py
yardstick_benchmark/games/minecraft/server/__init__.py
yardstick_benchmark/games/minecraft/server/papermc_cleanup.yml
yardstick_benchmark/games/minecraft/server/papermc_deploy.yml
yardstick_benchmark/games/minecraft/server/papermc_start.yml
yardstick_benchmark/games/minecraft/server/papermc_stop.yml
yardstick_benchmark/games/minecraft/server/server.properties.j2
yardstick_benchmark/games/minecraft/workload/__init__.py
yardstick_benchmark/games/minecraft/workload/set_spawn.js
yardstick_benchmark/games/minecraft/workload/walkaround_bot.js
yardstick_benchmark/games/minecraft/workload/walkaround_cleanup.yml
yardstick_benchmark/games/minecraft/workload/walkaround_deploy.yml
yardstick_benchmark/games/minecraft/workload/walkaround_start.yml
yardstick_benchmark/games/minecraft/workload/walkaround_stop.yml
yardstick_benchmark/games/minecraft/workload/walkaround_worker_bot.js
yardstick_benchmark/model.py
yardstick_benchmark/monitoring/__init__.py
yardstick_benchmark/monitoring/jolokia_get_minecraft_tick.py
yardstick_benchmark/monitoring/metrics-node001.csv
yardstick_benchmark/monitoring/metrics-node002.csv
yardstick_benchmark/monitoring/metrics-node031.csv
yardstick_benchmark/monitoring/telegraf.conf
yardstick_benchmark/monitoring/telegraf.conf.j2
yardstick_benchmark/monitoring/telegraf_cleanup.yml
yardstick_benchmark/monitoring/telegraf_deploy.yml
yardstick_benchmark/monitoring/telegraf_start.yml
yardstick_benchmark/monitoring/telegraf_stop.yml
yardstick_benchmark/provisioning.py
yardstick_benchmark-0.1.1.dist-info/METADATA
yardstick_benchmark-0.1.1.dist-info/WHEEL
yardstick_benchmark-0.1.1.dist-info/RECORD
