Metadata-Version: 2.1
Name: yardstick-benchmark
Version: 0.1.1
Summary: 
Author: Jesse Donkervliet
Author-email: j.donkervliet@gmail.com
Requires-Python: >=3.9,<4.0
Classifier: Programming Language :: Python :: 3
Classifier: Programming Language :: Python :: 3.9
Classifier: Programming Language :: Python :: 3.10
Classifier: Programming Language :: Python :: 3.11
Classifier: Programming Language :: Python :: 3.12
Requires-Dist: ansible (>=8.0.0,<9.0.0)
Requires-Dist: ansible-runner (>=2.3.3,<3.0.0)
Requires-Dist: plumbum (>=1.8.2,<2.0.0)
Requires-Dist: pyyaml (>=6.0,<7.0)
